annotation_exporter/__init__.py
annotation_exporter/annot_export.py
annotation_exporter/generic.py
annotation_exporter/main.py
annotation_exporter-1.0.7.dist-info/LICENSE
annotation_exporter-1.0.7.dist-info/METADATA
annotation_exporter-1.0.7.dist-info/WHEEL
annotation_exporter-1.0.7.dist-info/top_level.txt
annotation_exporter-1.0.7.dist-info/RECORD
